LICENSE
README.md
setup.py
lib/sqlalchemy_ingres/__init__.py
lib/sqlalchemy_ingres/_version.py
lib/sqlalchemy_ingres/base.py
lib/sqlalchemy_ingres/ingresdbi.py
lib/sqlalchemy_ingres/provision.py
lib/sqlalchemy_ingres/pyodbc.py
lib/sqlalchemy_ingres/requirements.py
lib/sqlalchemy_ingres/zxjdbc.py
lib/sqlalchemy_ingres.egg-info/PKG-INFO
lib/sqlalchemy_ingres.egg-info/SOURCES.txt
lib/sqlalchemy_ingres.egg-info/dependency_links.txt
lib/sqlalchemy_ingres.egg-info/entry_points.txt
lib/sqlalchemy_ingres.egg-info/requires.txt
lib/sqlalchemy_ingres.egg-info/top_level.txt