Metadata-Version: 2.1
Name: sqlalchemy-ingres
Version: 0.0.12
Summary: SQLAlchemy dialect for Actian databases; Actian Data Platform (nee Avalanche), Actian X, Ingres, and Vector
Home-page: https://github.com/ActianCorp/sqlalchemy-ingres
Author: Chris Clark
Author-email: Chris.Clark@actian.com
Maintainer: Michael Habiger
Maintainer-email: michael.habiger@hcl-software.com
License: Apache-2.0
Platform: any
Classifier: Development Status :: 4 - Beta
Classifier: License :: OSI Approved :: Apache Software License
Classifier: Operating System :: OS Independent
Classifier: Programming Language :: Python
Classifier: Programming Language :: Python :: 2
Classifier: Programming Language :: Python :: 2.7
Classifier: Programming Language :: Python :: 3
Classifier: Programming Language :: Python :: 3.12
Classifier: Topic :: Database
Classifier: Programming Language :: SQL
Provides-Extra: pyodbc
Provides-Extra: pypyodbc
Provides-Extra: all
License-File: LICENSE
